Metadata-Version: 2.1
Name: ohara
Version: 0.1.3
Summary: A collection of implementations of LLM, papers, and other models.
Home-page: https://github.com/joey00072/ohara
Author: joey00072
Author-email: 00shxf@gmail.com
Requires-Python: >=3.6
Requires-Dist: lightning >=2.3.0
Requires-Dist: transformers >=4.46.0
Requires-Dist: datasets >=3.1.0
Requires-Dist: wandb >=0.18.0
Requires-Dist: rich >=13.19.0
Requires-Dist: tensorboard >=2.18.0
